dbt2looker_bigquery/__init__.py
dbt2looker_bigquery/cli.py
dbt2looker_bigquery/enums.py
dbt2looker_bigquery/exceptions.py
dbt2looker_bigquery/utils.py
dbt2looker_bigquery/warnings.py
dbt2looker_bigquery/database/bigquery.py
dbt2looker_bigquery/database/models/bigqueryTable.py
dbt2looker_bigquery/generators/__init__.py
dbt2looker_bigquery/generators/dimension.py
dbt2looker_bigquery/generators/explore.py
dbt2looker_bigquery/generators/measure.py
dbt2looker_bigquery/generators/utils.py
dbt2looker_bigquery/generators/view.py
dbt2looker_bigquery/models/__init__.py
dbt2looker_bigquery/models/dbt.py
dbt2looker_bigquery/models/looker.py
dbt2looker_bigquery/parsers/__init__.py
dbt2looker_bigquery/parsers/base.py
dbt2looker_bigquery/parsers/catalog.py
dbt2looker_bigquery/parsers/exposure.py
dbt2looker_bigquery/parsers/model.py
dbt2looker_bigquery/parsers/type.py
dbt2looker_bigquery-0.23.10.dist-info/METADATA
dbt2looker_bigquery-0.23.10.dist-info/WHEEL
dbt2looker_bigquery-0.23.10.dist-info/entry_points.txt
dbt2looker_bigquery-0.23.10.dist-info/licenses/LICENSE
dbt2looker_bigquery-0.23.10.dist-info/RECORD
