Metadata-Version: 2.4
Name: dbt2looker-bigquery
Version: 0.23.10
Summary: Generate lookml view files from dbt models for Bigquery
License-File: LICENSE
Requires-Dist: datamodel-code-generator>=0.26.3
Requires-Dist: google-cloud-bigquery>=3.29.0
Requires-Dist: importlib-metadata>=4
Requires-Dist: lkml>=1.1
Requires-Dist: pre-commit>=4.0.1
Requires-Dist: pydantic>=2.9
Requires-Dist: pytest-cov>=6.0.0
Requires-Dist: pytest-mock>=3.14.0
Requires-Dist: pyyaml>=5.0
Requires-Dist: rich>=13.9.4
Requires-Dist: typing-extensions>=4.0
